api_gen
brittle_wit
tests
