Metadata-Version: 1.1
Name: brittle-wit
Version: 0.0.6
Summary: Brittle Wit is a Twitter Lib for Python.
Home-page: https://github.com/jbn/brittle_wit
Author: John Bjorn Nelson
Author-email: jbn@abreka.com
License: MIT
Keywords: twitter,twitter api,social networks
Platform: UNKNOWN
Classifier: Development Status :: 3 - Alpha
Classifier: Framework :: IPython
Classifier: Topic :: Communications
Classifier: Natural Language :: English
Classifier: License :: OSI Approved :: MIT License
Classifier: Operating System :: OS Independent
Classifier: Programming Language :: Python :: 3.5
Classifier: Topic :: Software Development :: Libraries :: Python Modules
